odoo/addons/l10n_br_fiscal_dfe/README.rst
odoo/addons/l10n_br_fiscal_dfe/__init__.py
odoo/addons/l10n_br_fiscal_dfe/__manifest__.py
odoo/addons/l10n_br_fiscal_dfe/constants/dfe.py
odoo/addons/l10n_br_fiscal_dfe/data/ir_cron.xml
odoo/addons/l10n_br_fiscal_dfe/i18n/l10n_br_fiscal_dfe.pot
odoo/addons/l10n_br_fiscal_dfe/i18n/pt_BR.po
odoo/addons/l10n_br_fiscal_dfe/models/__init__.py
odoo/addons/l10n_br_fiscal_dfe/models/attachment.py
odoo/addons/l10n_br_fiscal_dfe/models/dfe.py
odoo/addons/l10n_br_fiscal_dfe/models/document.py
odoo/addons/l10n_br_fiscal_dfe/models/res_company.py
odoo/addons/l10n_br_fiscal_dfe/readme/CONTRIBUTORS.md
odoo/addons/l10n_br_fiscal_dfe/readme/DESCRIPTION.md
odoo/addons/l10n_br_fiscal_dfe/security/ir.model.access.csv
odoo/addons/l10n_br_fiscal_dfe/static/description/icon.png
odoo/addons/l10n_br_fiscal_dfe/static/description/index.html
odoo/addons/l10n_br_fiscal_dfe/tests/__init__.py
odoo/addons/l10n_br_fiscal_dfe/tests/test_dfe.py
odoo/addons/l10n_br_fiscal_dfe/tools/__init__.py
odoo/addons/l10n_br_fiscal_dfe/tools/utils.py
odoo/addons/l10n_br_fiscal_dfe/views/l10n_br_fiscal_menu.xml
odoo/addons/l10n_br_fiscal_dfe/views/res_company_view.xml
odoo/addons/l10n_br_fiscal_dfe/views/dfe/dfe_views.xml
odoo14_addon_l10n_br_fiscal_dfe-14.0.2.5.0.dist-info/METADATA
odoo14_addon_l10n_br_fiscal_dfe-14.0.2.5.0.dist-info/WHEEL
odoo14_addon_l10n_br_fiscal_dfe-14.0.2.5.0.dist-info/top_level.txt
odoo14_addon_l10n_br_fiscal_dfe-14.0.2.5.0.dist-info/RECORD
